odoo/addons/mrp_routing/README.rst
odoo/addons/mrp_routing/__init__.py
odoo/addons/mrp_routing/__manifest__.py
odoo/addons/mrp_routing/data/sequence_data.xml
odoo/addons/mrp_routing/demo/routing_data.xml
odoo/addons/mrp_routing/i18n/it.po
odoo/addons/mrp_routing/i18n/mrp_routing.pot
odoo/addons/mrp_routing/models/__init__.py
odoo/addons/mrp_routing/models/mrp_bom.py
odoo/addons/mrp_routing/models/mrp_routing.py
odoo/addons/mrp_routing/models/mrp_routing_workcenter.py
odoo/addons/mrp_routing/models/mrp_routing_workcenter_template.py
odoo/addons/mrp_routing/readme/CONTRIBUTORS.rst
odoo/addons/mrp_routing/readme/DESCRIPTION.rst
odoo/addons/mrp_routing/readme/USAGE.rst
odoo/addons/mrp_routing/security/ir.model.access.csv
odoo/addons/mrp_routing/static/description/icon.png
odoo/addons/mrp_routing/static/description/index.html
odoo/addons/mrp_routing/tests/__init__.py
odoo/addons/mrp_routing/tests/test_manufacturing_routing.py
odoo/addons/mrp_routing/views/mrp_bom_view.xml
odoo/addons/mrp_routing/views/mrp_routing_view.xml
odoo/addons/mrp_routing/views/mrp_routing_workcenter_template_view.xml
odoo/addons/mrp_routing/views/mrp_routing_workcenter_view.xml
odoo14_addon_mrp_routing-14.0.1.0.1.dist-info/METADATA
odoo14_addon_mrp_routing-14.0.1.0.1.dist-info/WHEEL
odoo14_addon_mrp_routing-14.0.1.0.1.dist-info/top_level.txt
odoo14_addon_mrp_routing-14.0.1.0.1.dist-info/RECORD
